[
    {
        "id": 0,
        "name": "sample0",
        "email": "sample0@gmail.com",
        "password": "1000"
    },
    {
        "id": 1,
        "name": "sample1",
        "email": "sample1@gmail.com",
        "password": "1001"
    },
    {
        "id": 2,
        "name": "sample2",
        "email": "sample2@gmail.com",
        "password": "1002"
    },
    {
        "id": 3,
        "name": "sample3",
        "email": "sample3@gmail.com",
        "password": "1003"
    },
    {
        "id": 4,
        "name": "sample4",
        "email": "sample4@gmail.com",
        "password": "1004"
    },
    {
        "id": 5,
        "name": "sample5",
        "email": "sample5@gmail.com",
        "password": "1005"
    },
    {
        "id": 6,
        "name": "sample6",
        "email": "sample6@gmail.com",
        "password": "1006"
    },
    {
        "id": 7,
        "name": "sample7",
        "email": "sample7@gmail.com",
        "password": "1007"
    },
    {
        "id": 8,
        "name": "sample8",
        "email": "sample8@gmail.com",
        "password": "1008"
    },
    {
        "id": 9,
        "name": "sample9",
        "email": "sample9@gmail.com",
        "password": "1009"
    },
    {
        "id": 10,
        "name": "sample10",
        "email": "sample10@gmail.com",
        "password": "1010"
    },
    {
        "id": 11,
        "name": "sample11",
        "email": "sample11@gmail.com",
        "password": "1011"
    },
    {
        "id": 12,
        "name": "sample12",
        "email": "sample12@gmail.com",
        "password": "1012"
    },
    {
        "id": 13,
        "name": "sample13",
        "email": "sample13@gmail.com",
        "password": "1013"
    },
    {
        "id": 14,
        "name": "sample14",
        "email": "sample14@gmail.com",
        "password": "1014"
    },
    {
        "id": 15,
        "name": "sample15",
        "email": "sample15@gmail.com",
        "password": "1015"
    },
    {
        "id": 16,
        "name": "sample16",
        "email": "sample16@gmail.com",
        "password": "1016"
    },
    {
        "id": 17,
        "name": "sample17",
        "email": "sample17@gmail.com",
        "password": "1017"
    },
    {
        "id": 18,
        "name": "sample18",
        "email": "sample18@gmail.com",
        "password": "1018"
    },
    {
        "id": 19,
        "name": "sample19",
        "email": "sample19@gmail.com",
        "password": "1019"
    }
]